CHANGES.txt
LICENSE
MANIFEST.in
README.md
pytest.ini
requirements.txt
setup.py
ensemble/__init__.py
ensemble.egg-info/PKG-INFO
ensemble.egg-info/SOURCES.txt
ensemble.egg-info/dependency_links.txt
ensemble.egg-info/entry_points.txt
ensemble.egg-info/requires.txt
ensemble.egg-info/top_level.txt
ensemble/bin/__init__.py
ensemble/bin/ensemble_cli.py