Metadata-Version: 1.1
Name: ensemble
Version: 0.0.dev1
Summary: Open source linking for life cycle assessment
Home-page: https://example.com/
Author: OASES team
Author-email: cmutel@gmail.com
License: Copyright (c) 2018, OASES team
